MANIFEST.in
README.md
setup.py
bottle_tornadosocket/__init__.py
bottle_tornadosocket/server.py
bottle_tornadosocket.egg-info/PKG-INFO
bottle_tornadosocket.egg-info/SOURCES.txt
bottle_tornadosocket.egg-info/dependency_links.txt
bottle_tornadosocket.egg-info/requires.txt
bottle_tornadosocket.egg-info/top_level.txt