Metadata-Version: 1.1
Name: bottle-tornadosocket
Version: 0.13
Summary: WebSockets for bottle
Home-page: https://github.com/cime/bottle-tornadosocket
Author: cime
Author-email: cime@specialec.net
License: UNKNOWN
Platform: any
Classifier: Operating System :: OS Independent
Requires: bottle
Requires: tornado
